mplruler/__init__.py
mplruler/mplruler.py
mplruler-0.0.1.dist-info/LICENSE
mplruler-0.0.1.dist-info/METADATA
mplruler-0.0.1.dist-info/WHEEL
mplruler-0.0.1.dist-info/top_level.txt
mplruler-0.0.1.dist-info/RECORD
