Metadata-Version: 2.1
Name: mplruler
Version: 0.0.1
Summary: ruler for matplotlib's figure
Author: 15b3
License: MIT License
Project-URL: Homepage, https://github.com/15b3/mplruler
Project-URL: Issues, https://github.com/15b3/mplruler/issues
Classifier: Programming Language :: Python :: 3
Classifier: License :: OSI Approved :: MIT License
Requires-Python: >=3.6
License-File: LICENSE
Requires-Dist: matplotlib
Requires-Dist: numpy
Provides-Extra: dev
Requires-Dist: pytest ; extra == 'dev'
Requires-Dist: flake8 ; extra == 'dev'
Requires-Dist: mypy ; extra == 'dev'
Requires-Dist: black ; extra == 'dev'
Requires-Dist: isort ; extra == 'dev'
